Classfile /D:/Projects/arthas-demo/target/classes/com/itschenxiang/arthasdemo/controller/IndexController.class
  Last modified 2024Äê12ÔÂ18ÈÕ; size 3362 bytes
  MD5 checksum 93f29498b643850335c44cbc8416f06b
  Compiled from "IndexController.java"
public class com.itschenxiang.arthasdemo.controller.IndexController
  minor version: 0
  major version: 52
  flags: (0x0021) ACC_PUBLIC, ACC_SUPER
  this_class: #27                         // com/itschenxiang/arthasdemo/controller/IndexController
  super_class: #29                        // java/lang/Object
  interfaces: 0, fields: 2, methods: 7, attributes: 4
Constant pool:
    #1 = Methodref          #29.#58       // java/lang/Object."<init>":()V
    #2 = Class              #59           // java/util/concurrent/ThreadPoolExecutor
    #3 = Long               60l
    #5 = Fieldref           #60.#61       // java/util/concurrent/TimeUnit.SECONDS:Ljava/util/concurrent/TimeUnit;
    #6 = Class              #62           // java/util/concurrent/ArrayBlockingQueue
    #7 = Methodref          #6.#63        // java/util/concurrent/ArrayBlockingQueue."<init>":(I)V
    #8 = Class              #65           // org/apache/commons/lang3/concurrent/BasicThreadFactory$Builder
    #9 = Methodref          #8.#58        // org/apache/commons/lang3/concurrent/BasicThreadFactory$Builder."<init>":()V
   #10 = String             #68           // watch-lambda-pool-%d
   #11 = Methodref          #8.#69        // org/apache/commons/lang3/concurrent/BasicThreadFactory$Builder.namingPattern:(Ljava/lang/String;)Lorg/apache/commons/lang3/concurrent/BasicThreadFactory$Builder;
   #12 = Methodref          #8.#70        // org/apache/commons/lang3/concurrent/BasicThreadFactory$Builder.daemon:(Z)Lorg/apache/commons/lang3/concurrent/BasicThreadFactory$Builder;
   #13 = Methodref          #8.#71        // org/apache/commons/lang3/concurrent/BasicThreadFactory$Builder.build:()Lorg/apache/commons/lang3/concurrent/BasicThreadFactory;
   #14 = Methodref          #2.#72        // java/util/concurrent/ThreadPoolExecutor."<init>":(IIJLjava/util/concurrent/TimeUnit;Ljava/util/concurrent/BlockingQueue;Ljava/util/concurrent/ThreadFactory;)V
   #15 = Fieldref           #27.#73       // com/itschenxiang/arthasdemo/controller/IndexController.executorService:Ljava/util/concurrent/ExecutorService;
   #16 = InvokeDynamic      #0:#78        // #0:run:(Lcom/itschenxiang/arthasdemo/controller/IndexController;)Ljava/lang/Runnable;
   #17 = InterfaceMethodref #79.#80       // java/util/concurrent/ExecutorService.submit:(Ljava/lang/Runnable;)Ljava/util/concurrent/Future;
   #18 = String             #81           // Hello Lambda
   #19 = Methodref          #82.#83       // com/itschenxiang/arthasdemo/common/CommonResponse.success:(Ljava/lang/Object;)Lcom/itschenxiang/arthasdemo/common/CommonResponse;
   #20 = Fieldref           #27.#84       // com/itschenxiang/arthasdemo/controller/IndexController.log:Lorg/slf4j/Logger;
   #21 = String             #85           // watchLambda 1
   #22 = InterfaceMethodref #86.#87       // org/slf4j/Logger.info:(Ljava/lang/String;)V
   #23 = InvokeDynamic      #1:#78        // #1:run:(Lcom/itschenxiang/arthasdemo/controller/IndexController;)Ljava/lang/Runnable;
   #24 = String             #89           // watchLambda 2
   #25 = InvokeDynamic      #2:#91        // #2:run:()Ljava/lang/Runnable;
   #26 = String             #92           // watchLambda 3
   #27 = Class              #93           // com/itschenxiang/arthasdemo/controller/IndexController
   #28 = Methodref          #94.#95       // org/slf4j/LoggerFactory.getLogger:(Ljava/lang/Class;)Lorg/slf4j/Logger;
   #29 = Class              #96           // java/lang/Object
   #30 = Utf8               log
   #31 = Utf8               Lorg/slf4j/Logger;
   #32 = Utf8               executorService
   #33 = Utf8               Ljava/util/concurrent/ExecutorService;
   #34 = Utf8               <init>
   #35 = Utf8               ()V
   #36 = Utf8               Code
   #37 = Utf8               LineNumberTable
   #38 = Utf8               LocalVariableTable
   #39 = Utf8               this
   #40 = Utf8               Lcom/itschenxiang/arthasdemo/controller/IndexController;
   #41 = Utf8               init
   #42 = Utf8               RuntimeVisibleAnnotations
   #43 = Utf8               Ljavax/annotation/PostConstruct;
   #44 = Utf8               watchLambda
   #45 = Utf8               ()Lcom/itschenxiang/arthasdemo/common/CommonResponse;
   #46 = Utf8               Signature
   #47 = Utf8               ()Lcom/itschenxiang/arthasdemo/common/CommonResponse<Ljava/lang/String;>;
   #48 = Utf8               Lorg/springframework/web/bind/annotation/PostMapping;
   #49 = Utf8               value
   #50 = Utf8               /watchLambda
   #51 = Utf8               lambda$watchLambda$2
   #52 = Utf8               lambda$watchLambda$1
   #53 = Utf8               lambda$watchLambda$0
   #54 = Utf8               <clinit>
   #55 = Utf8               SourceFile
   #56 = Utf8               IndexController.java
   #57 = Utf8               Lorg/springframework/web/bind/annotation/RestController;
   #58 = NameAndType        #34:#35       // "<init>":()V
   #59 = Utf8               java/util/concurrent/ThreadPoolExecutor
   #60 = Class              #97           // java/util/concurrent/TimeUnit
   #61 = NameAndType        #98:#99       // SECONDS:Ljava/util/concurrent/TimeUnit;
   #62 = Utf8               java/util/concurrent/ArrayBlockingQueue
   #63 = NameAndType        #34:#100      // "<init>":(I)V
   #64 = Class              #101          // org/apache/commons/lang3/concurrent/BasicThreadFactory
   #65 = Utf8               org/apache/commons/lang3/concurrent/BasicThreadFactory$Builder
   #66 = Utf8               Builder
   #67 = Utf8               InnerClasses
   #68 = Utf8               watch-lambda-pool-%d
   #69 = NameAndType        #102:#103     // namingPattern:(Ljava/lang/String;)Lorg/apache/commons/lang3/concurrent/BasicThreadFactory$Builder;
   #70 = NameAndType        #104:#105     // daemon:(Z)Lorg/apache/commons/lang3/concurrent/BasicThreadFactory$Builder;
   #71 = NameAndType        #106:#107     // build:()Lorg/apache/commons/lang3/concurrent/BasicThreadFactory;
   #72 = NameAndType        #34:#108      // "<init>":(IIJLjava/util/concurrent/TimeUnit;Ljava/util/concurrent/BlockingQueue;Ljava/util/concurrent/ThreadFactory;)V
   #73 = NameAndType        #32:#33       // executorService:Ljava/util/concurrent/ExecutorService;
   #74 = Utf8               BootstrapMethods
   #75 = MethodHandle       6:#109        // REF_invokeStatic java/lang/invoke/LambdaMetafactory.metafactory:(Ljava/lang/invoke/MethodHandles$Lookup;Ljava/lang/String;Ljava/lang/invoke/MethodType;Ljava/lang/invoke/MethodType;Ljava/lang/invoke/MethodHandle;Ljava/lang/invoke/MethodType;)Ljava/lang/invoke/CallSite;
   #76 = MethodType         #35           //  ()V
   #77 = MethodHandle       7:#110        // REF_invokeSpecial com/itschenxiang/arthasdemo/controller/IndexController.lambda$watchLambda$2:()V
   #78 = NameAndType        #111:#112     // run:(Lcom/itschenxiang/arthasdemo/controller/IndexController;)Ljava/lang/Runnable;
   #79 = Class              #113          // java/util/concurrent/ExecutorService
   #80 = NameAndType        #114:#115     // submit:(Ljava/lang/Runnable;)Ljava/util/concurrent/Future;
   #81 = Utf8               Hello Lambda
   #82 = Class              #116          // com/itschenxiang/arthasdemo/common/CommonResponse
   #83 = NameAndType        #117:#118     // success:(Ljava/lang/Object;)Lcom/itschenxiang/arthasdemo/common/CommonResponse;
   #84 = NameAndType        #30:#31       // log:Lorg/slf4j/Logger;
   #85 = Utf8               watchLambda 1
   #86 = Class              #119          // org/slf4j/Logger
   #87 = NameAndType        #120:#121     // info:(Ljava/lang/String;)V
   #88 = MethodHandle       7:#122        // REF_invokeSpecial com/itschenxiang/arthasdemo/controller/IndexController.lambda$watchLambda$1:()V
   #89 = Utf8               watchLambda 2
   #90 = MethodHandle       6:#123        // REF_invokeStatic com/itschenxiang/arthasdemo/controller/IndexController.lambda$watchLambda$0:()V
   #91 = NameAndType        #111:#124     // run:()Ljava/lang/Runnable;
   #92 = Utf8               watchLambda 3
   #93 = Utf8               com/itschenxiang/arthasdemo/controller/IndexController
   #94 = Class              #125          // org/slf4j/LoggerFactory
   #95 = NameAndType        #126:#127     // getLogger:(Ljava/lang/Class;)Lorg/slf4j/Logger;
   #96 = Utf8               java/lang/Object
   #97 = Utf8               java/util/concurrent/TimeUnit
   #98 = Utf8               SECONDS
   #99 = Utf8               Ljava/util/concurrent/TimeUnit;
  #100 = Utf8               (I)V
  #101 = Utf8               org/apache/commons/lang3/concurrent/BasicThreadFactory
  #102 = Utf8               namingPattern
  #103 = Utf8               (Ljava/lang/String;)Lorg/apache/commons/lang3/concurrent/BasicThreadFactory$Builder;
  #104 = Utf8               daemon
  #105 = Utf8               (Z)Lorg/apache/commons/lang3/concurrent/BasicThreadFactory$Builder;
  #106 = Utf8               build
  #107 = Utf8               ()Lorg/apache/commons/lang3/concurrent/BasicThreadFactory;
  #108 = Utf8               (IIJLjava/util/concurrent/TimeUnit;Ljava/util/concurrent/BlockingQueue;Ljava/util/concurrent/ThreadFactory;)V
  #109 = Methodref          #128.#129     // java/lang/invoke/LambdaMetafactory.metafactory:(Ljava/lang/invoke/MethodHandles$Lookup;Ljava/lang/String;Ljava/lang/invoke/MethodType;Ljava/lang/invoke/MethodType;Ljava/lang/invoke/MethodHandle;Ljava/lang/invoke/MethodType;)Ljava/lang/invoke/CallSite;
  #110 = Methodref          #27.#130      // com/itschenxiang/arthasdemo/controller/IndexController.lambda$watchLambda$2:()V
  #111 = Utf8               run
  #112 = Utf8               (Lcom/itschenxiang/arthasdemo/controller/IndexController;)Ljava/lang/Runnable;
  #113 = Utf8               java/util/concurrent/ExecutorService
  #114 = Utf8               submit
  #115 = Utf8               (Ljava/lang/Runnable;)Ljava/util/concurrent/Future;
  #116 = Utf8               com/itschenxiang/arthasdemo/common/CommonResponse
  #117 = Utf8               success
  #118 = Utf8               (Ljava/lang/Object;)Lcom/itschenxiang/arthasdemo/common/CommonResponse;
  #119 = Utf8               org/slf4j/Logger
  #120 = Utf8               info
  #121 = Utf8               (Ljava/lang/String;)V
  #122 = Methodref          #27.#131      // com/itschenxiang/arthasdemo/controller/IndexController.lambda$watchLambda$1:()V
  #123 = Methodref          #27.#132      // com/itschenxiang/arthasdemo/controller/IndexController.lambda$watchLambda$0:()V
  #124 = Utf8               ()Ljava/lang/Runnable;
  #125 = Utf8               org/slf4j/LoggerFactory
  #126 = Utf8               getLogger
  #127 = Utf8               (Ljava/lang/Class;)Lorg/slf4j/Logger;
  #128 = Class              #133          // java/lang/invoke/LambdaMetafactory
  #129 = NameAndType        #134:#137     // metafactory:(Ljava/lang/invoke/MethodHandles$Lookup;Ljava/lang/String;Ljava/lang/invoke/MethodType;Ljava/lang/invoke/MethodType;Ljava/lang/invoke/MethodHandle;Ljava/lang/invoke/MethodType;)Ljava/lang/invoke/CallSite;
  #130 = NameAndType        #51:#35       // lambda$watchLambda$2:()V
  #131 = NameAndType        #52:#35       // lambda$watchLambda$1:()V
  #132 = NameAndType        #53:#35       // lambda$watchLambda$0:()V
  #133 = Utf8               java/lang/invoke/LambdaMetafactory
  #134 = Utf8               metafactory
  #135 = Class              #139          // java/lang/invoke/MethodHandles$Lookup
  #136 = Utf8               Lookup
  #137 = Utf8               (Ljava/lang/invoke/MethodHandles$Lookup;Ljava/lang/String;Ljava/lang/invoke/MethodType;Ljava/lang/invoke/MethodType;Ljava/lang/invoke/MethodHandle;Ljava/lang/invoke/MethodType;)Ljava/lang/invoke/CallSite;
  #138 = Class              #140          // java/lang/invoke/MethodHandles
  #139 = Utf8               java/lang/invoke/MethodHandles$Lookup
  #140 = Utf8               java/lang/invoke/MethodHandles
{
  public com.itschenxiang.arthasdemo.controller.IndexController();
    descriptor: ()V
    flags: (0x0001) ACC_PUBLIC
    Code:
      stack=1, locals=1, args_size=1
         0: aload_0
         1: invokespecial #1                  // Method java/lang/Object."<init>":()V
         4: return
      LineNumberTable:
        line 17: 0
      LocalVariableTable:
        Start  Length  Slot  Name   Signature
            0       5     0  this   Lcom/itschenxiang/arthasdemo/controller/IndexController;

  public void init();
    descriptor: ()V
    flags: (0x0001) ACC_PUBLIC
    Code:
      stack=11, locals=1, args_size=1
         0: aload_0
         1: new           #2                  // class java/util/concurrent/ThreadPoolExecutor
         4: dup
         5: iconst_3
         6: iconst_3
         7: ldc2_w        #3                  // long 60l
        10: getstatic     #5                  // Field java/util/concurrent/TimeUnit.SECONDS:Ljava/util/concurrent/TimeUnit;
        13: new           #6                  // class java/util/concurrent/ArrayBlockingQueue
        16: dup
        17: bipush        100
        19: invokespecial #7                  // Method java/util/concurrent/ArrayBlockingQueue."<init>":(I)V
        22: new           #8                  // class org/apache/commons/lang3/concurrent/BasicThreadFactory$Builder
        25: dup
        26: invokespecial #9                  // Method org/apache/commons/lang3/concurrent/BasicThreadFactory$Builder."<init>":()V
        29: ldc           #10                 // String watch-lambda-pool-%d
        31: invokevirtual #11                 // Method org/apache/commons/lang3/concurrent/BasicThreadFactory$Builder.namingPattern:(Ljava/lang/String;)Lorg/apache/commons/lang3/concurrent/BasicThreadFactory$Builder;
        34: iconst_1
        35: invokevirtual #12                 // Method org/apache/commons/lang3/concurrent/BasicThreadFactory$Builder.daemon:(Z)Lorg/apache/commons/lang3/concurrent/BasicThreadFactory$Builder;
        38: invokevirtual #13                 // Method org/apache/commons/lang3/concurrent/BasicThreadFactory$Builder.build:()Lorg/apache/commons/lang3/concurrent/BasicThreadFactory;
        41: invokespecial #14                 // Method java/util/concurrent/ThreadPoolExecutor."<init>":(IIJLjava/util/concurrent/TimeUnit;Ljava/util/concurrent/BlockingQueue;Ljava/util/concurrent/ThreadFactory;)V
        44: putfield      #15                 // Field executorService:Ljava/util/concurrent/ExecutorService;
        47: return
      LineNumberTable:
        line 23: 0
        line 26: 31
        line 27: 35
        line 28: 38
        line 29: 47
      LocalVariableTable:
        Start  Length  Slot  Name   Signature
            0      48     0  this   Lcom/itschenxiang/arthasdemo/controller/IndexController;
    RuntimeVisibleAnnotations:
      0: #43()
        javax.annotation.PostConstruct

  public com.itschenxiang.arthasdemo.common.CommonResponse<java.lang.String> watchLambda();
    descriptor: ()Lcom/itschenxiang/arthasdemo/common/CommonResponse;
    flags: (0x0001) ACC_PUBLIC
    Code:
      stack=2, locals=1, args_size=1
         0: aload_0
         1: getfield      #15                 // Field executorService:Ljava/util/concurrent/ExecutorService;
         4: aload_0
         5: invokedynamic #16,  0             // InvokeDynamic #0:run:(Lcom/itschenxiang/arthasdemo/controller/IndexController;)Ljava/lang/Runnable;
        10: invokeinterface #17,  2           // InterfaceMethod java/util/concurrent/ExecutorService.submit:(Ljava/lang/Runnable;)Ljava/util/concurrent/Future;
        15: pop
        16: ldc           #18                 // String Hello Lambda
        18: invokestatic  #19                 // Method com/itschenxiang/arthasdemo/common/CommonResponse.success:(Ljava/lang/Object;)Lcom/itschenxiang/arthasdemo/common/CommonResponse;
        21: areturn
      LineNumberTable:
        line 33: 0
        line 42: 16
      LocalVariableTable:
        Start  Length  Slot  Name   Signature
            0      22     0  this   Lcom/itschenxiang/arthasdemo/controller/IndexController;
    Signature: #47                          // ()Lcom/itschenxiang/arthasdemo/common/CommonResponse<Ljava/lang/String;>;
    RuntimeVisibleAnnotations:
      0: #48(#49=[s#50])
        org.springframework.web.bind.annotation.PostMapping(
          value=["/watchLambda"]
        )

  static {};
    descriptor: ()V
    flags: (0x0008) ACC_STATIC
    Code:
      stack=1, locals=0, args_size=0
         0: ldc           #27                 // class com/itschenxiang/arthasdemo/controller/IndexController
         2: invokestatic  #28                 // Method org/slf4j/LoggerFactory.getLogger:(Ljava/lang/Class;)Lorg/slf4j/Logger;
         5: putstatic     #20                 // Field log:Lorg/slf4j/Logger;
         8: return
      LineNumberTable:
        line 15: 0
}
SourceFile: "IndexController.java"
RuntimeVisibleAnnotations:
  0: #57()
    org.springframework.web.bind.annotation.RestController
InnerClasses:
  public static #66= #8 of #64;           // Builder=class org/apache/commons/lang3/concurrent/BasicThreadFactory$Builder of class org/apache/commons/lang3/concurrent/BasicThreadFactory
  public static final #136= #135 of #138; // Lookup=class java/lang/invoke/MethodHandles$Lookup of class java/lang/invoke/MethodHandles
BootstrapMethods:
  0: #75 REF_invokeStatic java/lang/invoke/LambdaMetafactory.metafactory:(Ljava/lang/invoke/MethodHandles$Lookup;Ljava/lang/String;Ljava/lang/invoke/MethodType;Ljava/lang/invoke/MethodType;Ljava/lang/invoke/MethodHandle;Ljava/lang/invoke/MethodType;)Ljava/lang/invoke/CallSite;
    Method arguments:
      #76 ()V
      #77 REF_invokeSpecial com/itschenxiang/arthasdemo/controller/IndexController.lambda$watchLambda$2:()V
      #76 ()V
  1: #75 REF_invokeStatic java/lang/invoke/LambdaMetafactory.metafactory:(Ljava/lang/invoke/MethodHandles$Lookup;Ljava/lang/String;Ljava/lang/invoke/MethodType;Ljava/lang/invoke/MethodType;Ljava/lang/invoke/MethodHandle;Ljava/lang/invoke/MethodType;)Ljava/lang/invoke/CallSite;
    Method arguments:
      #76 ()V
      #88 REF_invokeSpecial com/itschenxiang/arthasdemo/controller/IndexController.lambda$watchLambda$1:()V
      #76 ()V
  2: #75 REF_invokeStatic java/lang/invoke/LambdaMetafactory.metafactory:(Ljava/lang/invoke/MethodHandles$Lookup;Ljava/lang/String;Ljava/lang/invoke/MethodType;Ljava/lang/invoke/MethodType;Ljava/lang/invoke/MethodHandle;Ljava/lang/invoke/MethodType;)Ljava/lang/invoke/CallSite;
    Method arguments:
      #76 ()V
      #90 REF_invokeStatic com/itschenxiang/arthasdemo/controller/IndexController.lambda$watchLambda$0:()V
      #76 ()V
